coin_api_mcp/__init__.py
coin_api_mcp/__main__.py
coin_api_mcp/server.py
mseep_coin_api_mcp-0.1.3.dist-info/METADATA
mseep_coin_api_mcp-0.1.3.dist-info/WHEEL
mseep_coin_api_mcp-0.1.3.dist-info/entry_points.txt
mseep_coin_api_mcp-0.1.3.dist-info/RECORD
